Metadata-Version: 2.1
Name: pelican-webassets-babeljsx
Version: 1.0.0
Summary: A simple plugin that registers the babeljsx Jinja2 filter.
Home-page: https://github.com/rhooper/pelican-webassets-babeljsx
Author: R Hooper
Author-email: rhooper@toybox.ca
License: MIT
Project-URL: Bug Tracker, https://github.com/rhooper/pelican-webassets-babeljsx/issues
Project-URL: Source, https://github.com/rhooper/pelican-webassets-babeljsx/
Keywords: pelican webassets babeljsx plugin
Platform: UNKNOWN
Classifier: Programming Language :: Python :: 3
Classifier: License :: OSI Approved :: MIT License
Classifier: Operating System :: OS Independent
Requires-Python: >=3.6
